{"state":"warEnded","teamSize":30,"preparationStartTime":"20200801T144508.000Z","startTime":"20200802T144423.000Z","endTime":"20200803T152330.000Z","clan":{"tag":"#PYCLJJ8U","name":"BB1WarDogs","badgeUrls":{"small":"https://api-assets.clashofclans.com/badges/70/CUF7H_euOawV5fGSiF_qzuAJLijIDxtpWqUiVHF87aQ.png","large":"https://api-assets.clashofclans.com/badges/512/CUF7H_euOawV5fGSiF_qzuAJLijIDxtpWqUiVHF87aQ.png","medium":"https://api-assets.clashofclans.com/badges/200/CUF7H_euOawV5fGSiF_qzuAJLijIDxtpWqUiVHF87aQ.png"},"clanLevel":14,"attacks":30,"stars":72,"destructionPercentage":85.43333333333334,"members":[{"tag":"#8QJ9GC8G","name":"drjorobinson","townhallLevel":13,"mapPosition":4,"attacks":[{"attackerTag":"#8QJ9GC8G","defenderTag":"#2U80C80C9","stars":2,"destructionPercentage":66,"order":28}],"opponentAttacks":1,"bestOpponentAttack":{"attackerTag":"#2U80C80C9","defenderTag":"#8QJ9GC8G","stars":2,"destructionPercentage":69,"order":31}},{"tag":"#2P8PLJC0Y","name":"melky","townhallLevel":13,"mapPosition":17,"attacks":[{"attackerTag":"#2P8PLJC0Y","defenderTag":"#9JURLPY99","stars":2,"destructionPercentage":92,"order":46}],"opponentAttacks":1,"bestOpponentAttack":{"attackerTag":"#UCQQL2UV","defenderTag":"#2P8PLJC0Y","stars":2,"destructionPercentage":82,"order":47}},{"tag":"#LP0CYURV","name":"Rischi","townhallLevel":13,"mapPosition":19,"attacks":[{"attackerTag":"#LP0CYURV","defenderTag":"#92VUYLYQ2","stars":3,"destructionPercentage":100,"order":51}],"opponentAttacks":1,"bestOpponentAttack":{"attackerTag":"#Y92VJ9JUU","defenderTag":"#LP0CYURV","stars":2,"destructionPercentage":61,"order":52}},{"tag":"#2YQ9QLL8","name":"Logic","townhallLevel":12,"mapPosition":28,"attacks":[{"attackerTag":"#2YQ9QLL8","defenderTag":"#8CQVUQ9YJ","stars":2,"destructionPercentage":50,"order":24}],"opponentAttacks":1,"bestOpponentAttack":{"attackerTag":"#9U080VV0Y","defenderTag":"#2YQ9QLL8","stars":3,"destructionPercentage":100,"order":32}},{"tag":"#8YP2PLCU8","name":"Alameed","townhallLevel":12,"mapPosition":35,"attacks":[{"attackerTag":"#8YP2PLCU8","defenderTag":"#9JL2RJUVG","stars":2,"destructionPercentage":54,"order":17}],"opponentAttacks":1,"bestOpponentAttack":{"attackerTag":"#92VUYLYQ2","defenderTag":"#8YP2PLCU8","stars":3,"destructionPercentage":100,"order":1}},{"tag":"#UY9QGLLU","name":"melkuna","townhallLevel":13,"mapPosition":8,"attacks":[{"attackerTag":"#UY9QGLLU","defenderTag":"#9PQYCGUL8","stars":3,"destructionPercentage":100,"order":45}],"opponentAttacks":1,"bestOpponentAttack":{"attackerTag":"#Y20PP98L0","defenderTag":"#UY9QGLLU","stars":1,"destructionPercentage":42,"order":49}},{"tag":"#UUVJLJ2P","name":"-=[slimjim29]=-","townhallLevel":13,"mapPosition":15,"attacks":[{"attackerTag":"#UUVJLJ2P","defenderTag":"#YLGY9YRPG","stars":2,"destructionPercentage":96,"order":5}],"opponentAttacks":1,"bestOpponentAttack":{"attackerTag":"#Y8G828QVL","defenderTag":"#UUVJLJ2P","stars":2,"destructionPercentage":76,"order":8}},{"tag":"#8L28802V","name":"SummeR","townhallLevel":12,"mapPosition":30,"attacks":[{"attackerTag":"#8L28802V","defenderTag":"#2C0YQY2JC","stars":3,"destructionPercentage":100,"order":2}],"opponentAttacks":1,"bestOpponentAttack":{"attackerTag":"#9PQYCGUL8","defenderTag":"#8L28802V","stars":2,"destructionPercentage":56,"order":37}},{"tag":"#RVRC8PPP","name":"canobe24","townhallLevel":12,"mapPosition":33,"attacks":[{"attackerTag":"#RVRC8PPP","defenderTag":"#PJ9RLC98G","stars":2,"destructionPercentage":60,"order":29}],"opponentAttacks":1,"bestOpponentAttack":{"attackerTag":"#8P8ULV0G8","defenderTag":"#RVRC8PPP","stars":3,"destructionPercentage":100,"order":9}},{"tag":"#9Y9008VQC","name":"WobblyWallaby","townhallLevel":12,"mapPosition":29,"attacks":[{"attackerTag":"#9Y9008VQC","defenderTag":"#Y92VJ9JUU","stars":3,"destructionPercentage":100,"order":15}],"opponentAttacks":1,"bestOpponentAttack":{"attackerTag":"#9JURLPY99","defenderTag":"#9Y9008VQC","stars":3,"destructionPercentage":100,"order":34}},{"tag":"#LUCYV8PC","name":"Kosherwarrior","townhallLevel":13,"mapPosition":7,"attacks":[{"attackerTag":"#LUCYV8PC","defenderTag":"#Y20PP98L0","stars":3,"destructionPercentage":100,"order":11}],"opponentAttacks":1,"bestOpponentAttack":{"attackerTag":"#Y8CQ8GGYG","defenderTag":"#LUCYV8PC","stars":2,"destructionPercentage":97,"order":56}},{"tag":"#8VV2QJV0","name":"bearful","townhallLevel":13,"mapPosition":20,"attacks":[{"attackerTag":"#8VV2QJV0","defenderTag":"#9QPCJUJY8","stars":2,"destructionPercentage":71,"order":25}],"opponentAttacks":1,"bestOpponentAttack":{"attackerTag":"#Y099J0YR2","defenderTag":"#8VV2QJV0","stars":2,"destructionPercentage":67,"order":54}},{"tag":"#2J29VQL2","name":"chief","townhallLevel":13,"mapPosition":13,"attacks":[{"attackerTag":"#2J29VQL2","defenderTag":"#Y20PVR2L","stars":3,"destructionPercentage":100,"order":42}],"opponentAttacks":1,"bestOpponentAttack":{"attackerTag":"#8GCYJVUV9","defenderTag":"#2J29VQL2","stars":2,"destructionPercentage":69,"order":53}},{"tag":"#GU2GGQC9","name":"༺࿅vBlvckbird࿅༻","townhallLevel":13,"mapPosition":6,"attacks":[{"attackerTag":"#GU2GGQC9","defenderTag":"#9QUYGV2J8","stars":2,"destructionPercentage":60,"order":21}],"opponentAttacks":1,"bestOpponentAttack":{"attackerTag":"#90JLVJ0PJ","defenderTag":"#GU2GGQC9","stars":2,"destructionPercentage":98,"order":55}},{"tag":"#2RU2LR9JJ","name":"Supreme","townhallLevel":13,"mapPosition":10,"attacks":[{"attackerTag":"#2RU2LR9JJ","defenderTag":"#9U080VV0Y","stars":2,"destructionPercentage":77,"order":7}],"opponentAttacks":1,"bestOpponentAttack":{"attackerTag":"#9J89Q9VJY","defenderTag":"#2RU2LR9JJ","stars":2,"destructionPercentage":83,"order":50}},{"tag":"#PJ9UUUQJ","name":"Tsb_ZOOMBIII","townhallLevel":13,"mapPosition":18,"attacks":[{"attackerTag":"#PJ9UUUQJ","defenderTag":"#UCQQL2UV","stars":2,"destructionPercentage":97,"order":13}],"opponentAttacks":1,"bestOpponentAttack":{"attackerTag":"#9QUYGV2J8","defenderTag":"#PJ9UUUQJ","stars":2,"destructionPercentage":55,"order":35}},{"tag":"#82P89CU2","name":"Ⓝⓐⓒ⑦⓪④","townhallLevel":12,"mapPosition":23,"attacks":[{"attackerTag":"#82P89CU2","defenderTag":"#Y8G828QVL","stars":2,"destructionPercentage":93,"order":16}],"opponentAttacks":1,"bestOpponentAttack":{"attackerTag":"#2C0YQY2JC","defenderTag":"#82P89CU2","stars":2,"destructionPercentage":99,"order":38}},{"tag":"#2GJRL2GRR","name":"C2","townhallLevel":12,"mapPosition":34,"attacks":[{"attackerTag":"#2GJRL2GRR","defenderTag":"#90JLVJ0PJ","stars":2,"destructionPercentage":62,"order":19}],"opponentAttacks":1,"bestOpponentAttack":{"attackerTag":"#9JL2RJUVG","defenderTag":"#2GJRL2GRR","stars":3,"destructionPercentage":100,"order":3}},{"tag":"#2GCQLPLQL","name":"Paul98","townhallLevel":12,"mapPosition":21,"attacks":[{"attackerTag":"#2GCQLPLQL","defenderTag":"#9J89Q9VJY","stars":1,"destructionPercentage":67,"order":12}],"opponentAttacks":1,"bestOpponentAttack":{"attackerTag":"#G9RP2GR","defenderTag":"#2GCQLPLQL","stars":2,"destructionPercentage":84,"order":39}},{"tag":"#8Y0QGP2Q9","name":"TeeOknee","townhallLevel":12,"mapPosition":27,"attacks":[{"attackerTag":"#8Y0QGP2Q9","defenderTag":"#9QRLGYV89","stars":2,"destructionPercentage":86,"order":10}],"opponentAttacks":1,"bestOpponentAttack":{"attackerTag":"#89GCGVYLC","defenderTag":"#8Y0QGP2Q9","stars":3,"destructionPercentage":100,"order":18}},{"tag":"#8JY9RL2CU","name":"migdad","townhallLevel":13,"mapPosition":16,"attacks":[{"attackerTag":"#8JY9RL2CU","defenderTag":"#9LJJUYUJQ","stars":3,"destructionPercentage":100,"order":27}],"opponentAttacks":1,"bestOpponentAttack":{"attackerTag":"#PVJ9QRJ80","defenderTag":"#8JY9RL2CU","stars":2,"destructionPercentage":77,"order":58}},{"tag":"#2R9LCYUP0","name":"Neel","townhallLevel":13,"mapPosition":2,"attacks":[{"attackerTag":"#2R9LCYUP0","defenderTag":"#8U2YQJ9J9","stars":3,"destructionPercentage":100,"order":36}],"opponentAttacks":1,"bestOpponentAttack":{"attackerTag":"#9QPCJUJY8","defenderTag":"#2R9LCYUP0","stars":2,"destructionPercentage":73,"order":41}},{"tag":"#PRYRYRRJ","name":"(<calvin>)","townhallLevel":13,"mapPosition":3,"attacks":[{"attackerTag":"#PRYRYRRJ","defenderTag":"#8P8ULV0G8","stars":3,"destructionPercentage":100,"order":20}],"opponentAttacks":1,"bestOpponentAttack":{"attackerTag":"#9QRLGYV89","defenderTag":"#PRYRYRRJ","stars":2,"destructionPercentage":58,"order":43}},{"tag":"#92UG22LL9","name":"Dave","townhallLevel":12,"mapPosition":24,"attacks":[{"attackerTag":"#92UG22LL9","defenderTag":"#Y099J0YR2","stars":2,"destructionPercentage":69,"order":26}],"opponentAttacks":1,"bestOpponentAttack":{"attackerTag":"#YLGY9YRPG","defenderTag":"#92UG22LL9","stars":3,"destructionPercentage":100,"order":6}},{"tag":"#80QGC8RGP","name":"HitMaN","townhallLevel":13,"mapPosition":14,"attacks":[{"attackerTag":"#80QGC8RGP","defenderTag":"#G9RP2GR","stars":3,"destructionPercentage":100,"order":59}],"opponentAttacks":0},{"tag":"#8GPCP09P","name":"Randy","townhallLevel":13,"mapPosition":1,"attacks":[{"attackerTag":"#8GPCP09P","defenderTag":"#8GCYJVUV9","stars":3,"destructionPercentage":100,"order":23}],"opponentAttacks":1,"bestOpponentAttack":{"attackerTag":"#9LJJUYUJQ","defenderTag":"#8GPCP09P","stars":2,"destructionPercentage":52,"order":40}},{"tag":"#229YQYC92","name":"༺ིུ࿂Remix࿂ིུ༻","townhallLevel":13,"mapPosition":12,"attacks":[{"attackerTag":"#229YQYC92","defenderTag":"#89GCGVYLC","stars":2,"destructionPercentage":91,"order":33}],"opponentAttacks":1,"bestOpponentAttack":{"attackerTag":"#8U2YQJ9J9","defenderTag":"#229YQYC92","stars":2,"destructionPercentage":84,"order":4}},{"tag":"#RVJLGUG0","name":"LiL Randy","townhallLevel":13,"mapPosition":5,"attacks":[{"attackerTag":"#RVJLGUG0","defenderTag":"#9Y82YQ02R","stars":3,"destructionPercentage":100,"order":22}],"opponentAttacks":1,"bestOpponentAttack":{"attackerTag":"#Y20PVR2L","defenderTag":"#RVJLGUG0","stars":2,"destructionPercentage":68,"order":44}},{"tag":"#820ULLUQ0","name":"Milan","townhallLevel":12,"mapPosition":25,"attacks":[{"attackerTag":"#820ULLUQ0","defenderTag":"#Y8CQ8GGYG","stars":2,"destructionPercentage":72,"order":14}],"opponentAttacks":1,"bestOpponentAttack":{"attackerTag":"#PJ9RLC98G","defenderTag":"#820ULLUQ0","stars":2,"destructionPercentage":95,"order":30}},{"tag":"#2Q0PQC8QL","name":"Donater","townhallLevel":13,"mapPosition":11,"attacks":[{"attackerTag":"#2Q0PQC8QL","defenderTag":"#PVJ9QRJ80","stars":3,"destructionPercentage":100,"order":48}],"opponentAttacks":1,"bestOpponentAttack":{"attackerTag":"#9Y82YQ02R","defenderTag":"#2Q0PQC8QL","stars":2,"destructionPercentage":80,"order":57}}]},"opponent":{"tag":"#90GJVY09","name":"THE DRAGON KING","badgeUrls":{"small":"https://api-assets.clashofclans.com/badges/70/_helDUsQHYasd7wW3yc-_-VUfgsSARVZ-n62lj3P72M.png","large":"https://api-assets.clashofclans.com/badges/512/_helDUsQHYasd7wW3yc-_-VUfgsSARVZ-n62lj3P72M.png","medium":"https://api-assets.clashofclans.com/badges/200/_helDUsQHYasd7wW3yc-_-VUfgsSARVZ-n62lj3P72M.png"},"clanLevel":20,"attacks":29,"stars":64,"destructionPercentage":77.5,"members":[{"tag":"#8GCYJVUV9","name":"ASLAM","townhallLevel":13,"mapPosition":10,"attacks":[{"attackerTag":"#8GCYJVUV9","defenderTag":"#2J29VQL2","stars":2,"destructionPercentage":69,"order":53}],"opponentAttacks":1,"bestOpponentAttack":{"attackerTag":"#8GPCP09P","defenderTag":"#8GCYJVUV9","stars":3,"destructionPercentage":100,"order":23}},{"tag":"#90JLVJ0PJ","name":"MD.ÑØBËL MÏÃH","townhallLevel":13,"mapPosition":2,"attacks":[{"attackerTag":"#90JLVJ0PJ","defenderTag":"#GU2GGQC9","stars":2,"destructionPercentage":98,"order":55}],"opponentAttacks":1,"bestOpponentAttack":{"attackerTag":"#2GJRL2GRR","defenderTag":"#90JLVJ0PJ","stars":2,"destructionPercentage":62,"order":19}},{"tag":"#8CQVUQ9YJ","name":"★★Lasker Tonu★★","townhallLevel":13,"mapPosition":34,"opponentAttacks":1,"bestOpponentAttack":{"attackerTag":"#2YQ9QLL8","defenderTag":"#8CQVUQ9YJ","stars":2,"destructionPercentage":50,"order":24}},{"tag":"#9QUYGV2J8","name":"Thaslim Rana","townhallLevel":13,"mapPosition":3,"attacks":[{"attackerTag":"#9QUYGV2J8","defenderTag":"#PJ9UUUQJ","stars":2,"destructionPercentage":55,"order":35}],"opponentAttacks":1,"bestOpponentAttack":{"attackerTag":"#GU2GGQC9","defenderTag":"#9QUYGV2J8","stars":2,"destructionPercentage":60,"order":21}},{"tag":"#9JL2RJUVG","name":"MD♧SHUVO♧","townhallLevel":13,"mapPosition":31,"attacks":[{"attackerTag":"#9JL2RJUVG","defenderTag":"#2GJRL2GRR","stars":3,"destructionPercentage":100,"order":3}],"opponentAttacks":1,"bestOpponentAttack":{"attackerTag":"#8YP2PLCU8","defenderTag":"#9JL2RJUVG","stars":2,"destructionPercentage":54,"order":17}},{"tag":"#9U080VV0Y","name":"THASLIM RANA /2","townhallLevel":13,"mapPosition":11,"attacks":[{"attackerTag":"#9U080VV0Y","defenderTag":"#2YQ9QLL8","stars":3,"destructionPercentage":100,"order":32}],"opponentAttacks":1,"bestOpponentAttack":{"attackerTag":"#2RU2LR9JJ","defenderTag":"#9U080VV0Y","stars":2,"destructionPercentage":77,"order":7}},{"tag":"#9PQYCGUL8","name":"Hannan","townhallLevel":13,"mapPosition":13,"attacks":[{"attackerTag":"#9PQYCGUL8","defenderTag":"#8L28802V","stars":2,"destructionPercentage":56,"order":37}],"opponentAttacks":1,"bestOpponentAttack":{"attackerTag":"#UY9QGLLU","defenderTag":"#9PQYCGUL8","stars":3,"destructionPercentage":100,"order":45}},{"tag":"#92VUYLYQ2","name":"night fury","townhallLevel":13,"mapPosition":35,"attacks":[{"attackerTag":"#92VUYLYQ2","defenderTag":"#8YP2PLCU8","stars":3,"destructionPercentage":100,"order":1}],"opponentAttacks":1,"bestOpponentAttack":{"attackerTag":"#LP0CYURV","defenderTag":"#92VUYLYQ2","stars":3,"destructionPercentage":100,"order":51}},{"tag":"#UCQQL2UV","name":"Pritam","townhallLevel":13,"mapPosition":17,"attacks":[{"attackerTag":"#UCQQL2UV","defenderTag":"#2P8PLJC0Y","stars":2,"destructionPercentage":82,"order":47}],"opponentAttacks":1,"bestOpponentAttack":{"attackerTag":"#PJ9UUUQJ","defenderTag":"#UCQQL2UV","stars":2,"destructionPercentage":97,"order":13}},{"tag":"#8U2YQJ9J9","name":"faysal","townhallLevel":13,"mapPosition":20,"attacks":[{"attackerTag":"#8U2YQJ9J9","defenderTag":"#229YQYC92","stars":2,"destructionPercentage":84,"order":4}],"opponentAttacks":1,"bestOpponentAttack":{"attackerTag":"#2R9LCYUP0","defenderTag":"#8U2YQJ9J9","stars":3,"destructionPercentage":100,"order":36}},{"tag":"#9JURLPY99","name":"Md Mehedi Hasan","townhallLevel":13,"mapPosition":22,"attacks":[{"attackerTag":"#9JURLPY99","defenderTag":"#9Y9008VQC","stars":3,"destructionPercentage":100,"order":34}],"opponentAttacks":1,"bestOpponentAttack":{"attackerTag":"#2P8PLJC0Y","defenderTag":"#9JURLPY99","stars":2,"destructionPercentage":92,"order":46}},{"tag":"#8P8ULV0G8","name":"Thor","townhallLevel":13,"mapPosition":32,"attacks":[{"attackerTag":"#8P8ULV0G8","defenderTag":"#RVRC8PPP","stars":3,"destructionPercentage":100,"order":9}],"opponentAttacks":1,"bestOpponentAttack":{"attackerTag":"#PRYRYRRJ","defenderTag":"#8P8ULV0G8","stars":3,"destructionPercentage":100,"order":20}},{"tag":"#89GCGVYLC","name":"Sk Solaiman","townhallLevel":13,"mapPosition":27,"attacks":[{"attackerTag":"#89GCGVYLC","defenderTag":"#8Y0QGP2Q9","stars":3,"destructionPercentage":100,"order":18}],"opponentAttacks":1,"bestOpponentAttack":{"attackerTag":"#229YQYC92","defenderTag":"#89GCGVYLC","stars":2,"destructionPercentage":91,"order":33}},{"tag":"#9QRLGYV89","name":"MD.ÑØBËL MÏÃH 2","townhallLevel":13,"mapPosition":15,"attacks":[{"attackerTag":"#9QRLGYV89","defenderTag":"#PRYRYRRJ","stars":2,"destructionPercentage":58,"order":43}],"opponentAttacks":1,"bestOpponentAttack":{"attackerTag":"#8Y0QGP2Q9","defenderTag":"#9QRLGYV89","stars":2,"destructionPercentage":86,"order":10}},{"tag":"#Y8CQ8GGYG","name":"DJ VIROUS","townhallLevel":13,"mapPosition":1,"attacks":[{"attackerTag":"#Y8CQ8GGYG","defenderTag":"#LUCYV8PC","stars":2,"destructionPercentage":97,"order":56}],"opponentAttacks":1,"bestOpponentAttack":{"attackerTag":"#820ULLUQ0","defenderTag":"#Y8CQ8GGYG","stars":2,"destructionPercentage":72,"order":14}},{"tag":"#2U80C80C9","name":"SizaN","townhallLevel":13,"mapPosition":8,"attacks":[{"attackerTag":"#2U80C80C9","defenderTag":"#8QJ9GC8G","stars":2,"destructionPercentage":69,"order":31}],"opponentAttacks":1,"bestOpponentAttack":{"attackerTag":"#8QJ9GC8G","defenderTag":"#2U80C80C9","stars":2,"destructionPercentage":66,"order":28}},{"tag":"#9J89Q9VJY","name":"SK SÃGØR SØÏKÃT","townhallLevel":13,"mapPosition":7,"attacks":[{"attackerTag":"#9J89Q9VJY","defenderTag":"#2RU2LR9JJ","stars":2,"destructionPercentage":83,"order":50}],"opponentAttacks":1,"bestOpponentAttack":{"attackerTag":"#2GCQLPLQL","defenderTag":"#9J89Q9VJY","stars":1,"destructionPercentage":67,"order":12}},{"tag":"#2C0YQY2JC","name":"$hawon_2","townhallLevel":13,"mapPosition":29,"attacks":[{"attackerTag":"#2C0YQY2JC","defenderTag":"#82P89CU2","stars":2,"destructionPercentage":99,"order":38}],"opponentAttacks":1,"bestOpponentAttack":{"attackerTag":"#8L28802V","defenderTag":"#2C0YQY2JC","stars":3,"destructionPercentage":100,"order":2}},{"tag":"#Y20PP98L0","name":"Denger man","townhallLevel":13,"mapPosition":18,"attacks":[{"attackerTag":"#Y20PP98L0","defenderTag":"#UY9QGLLU","stars":1,"destructionPercentage":42,"order":49}],"opponentAttacks":1,"bestOpponentAttack":{"attackerTag":"#LUCYV8PC","defenderTag":"#Y20PP98L0","stars":3,"destructionPercentage":100,"order":11}},{"tag":"#Y92VJ9JUU","name":"Dipua","townhallLevel":13,"mapPosition":26,"attacks":[{"attackerTag":"#Y92VJ9JUU","defenderTag":"#LP0CYURV","stars":2,"destructionPercentage":61,"order":52}],"opponentAttacks":1,"bestOpponentAttack":{"attackerTag":"#9Y9008VQC","defenderTag":"#Y92VJ9JUU","stars":3,"destructionPercentage":100,"order":15}},{"tag":"#PVJ9QRJ80","name":"Dead man","townhallLevel":13,"mapPosition":4,"attacks":[{"attackerTag":"#PVJ9QRJ80","defenderTag":"#8JY9RL2CU","stars":2,"destructionPercentage":77,"order":58}],"opponentAttacks":1,"bestOpponentAttack":{"attackerTag":"#2Q0PQC8QL","defenderTag":"#PVJ9QRJ80","stars":3,"destructionPercentage":100,"order":48}},{"tag":"#YLGY9YRPG","name":"Soriful Islam","townhallLevel":13,"mapPosition":19,"attacks":[{"attackerTag":"#YLGY9YRPG","defenderTag":"#92UG22LL9","stars":3,"destructionPercentage":100,"order":6}],"opponentAttacks":1,"bestOpponentAttack":{"attackerTag":"#UUVJLJ2P","defenderTag":"#YLGY9YRPG","stars":2,"destructionPercentage":96,"order":5}},{"tag":"#G9RP2GR","name":"SHAWON","townhallLevel":13,"mapPosition":25,"attacks":[{"attackerTag":"#G9RP2GR","defenderTag":"#2GCQLPLQL","stars":2,"destructionPercentage":84,"order":39}],"opponentAttacks":1,"bestOpponentAttack":{"attackerTag":"#80QGC8RGP","defenderTag":"#G9RP2GR","stars":3,"destructionPercentage":100,"order":59}},{"tag":"#9Y82YQ02R","name":"RM RAIHAN","townhallLevel":13,"mapPosition":5,"attacks":[{"attackerTag":"#9Y82YQ02R","defenderTag":"#2Q0PQC8QL","stars":2,"destructionPercentage":80,"order":57}],"opponentAttacks":1,"bestOpponentAttack":{"attackerTag":"#RVJLGUG0","defenderTag":"#9Y82YQ02R","stars":3,"destructionPercentage":100,"order":22}},{"tag":"#Y20PVR2L","name":"MX boy MoStAk","townhallLevel":13,"mapPosition":16,"attacks":[{"attackerTag":"#Y20PVR2L","defenderTag":"#RVJLGUG0","stars":2,"destructionPercentage":68,"order":44}],"opponentAttacks":1,"bestOpponentAttack":{"attackerTag":"#2J29VQL2","defenderTag":"#Y20PVR2L","stars":3,"destructionPercentage":100,"order":42}},{"tag":"#9QPCJUJY8","name":"RM.RAIHAN.MIA.2","townhallLevel":13,"mapPosition":12,"attacks":[{"attackerTag":"#9QPCJUJY8","defenderTag":"#2R9LCYUP0","stars":2,"destructionPercentage":73,"order":41}],"opponentAttacks":1,"bestOpponentAttack":{"attackerTag":"#8VV2QJV0","defenderTag":"#9QPCJUJY8","stars":2,"destructionPercentage":71,"order":25}},{"tag":"#Y099J0YR2","name":"joy","townhallLevel":13,"mapPosition":9,"attacks":[{"attackerTag":"#Y099J0YR2","defenderTag":"#8VV2QJV0","stars":2,"destructionPercentage":67,"order":54}],"opponentAttacks":1,"bestOpponentAttack":{"attackerTag":"#92UG22LL9","defenderTag":"#Y099J0YR2","stars":2,"destructionPercentage":69,"order":26}},{"tag":"#PJ9RLC98G","name":"RAVINDRA JAIN","townhallLevel":13,"mapPosition":28,"attacks":[{"attackerTag":"#PJ9RLC98G","defenderTag":"#820ULLUQ0","stars":2,"destructionPercentage":95,"order":30}],"opponentAttacks":1,"bestOpponentAttack":{"attackerTag":"#RVRC8PPP","defenderTag":"#PJ9RLC98G","stars":2,"destructionPercentage":60,"order":29}},{"tag":"#Y8G828QVL","name":"Mh Nuralom Af","townhallLevel":13,"mapPosition":6,"attacks":[{"attackerTag":"#Y8G828QVL","defenderTag":"#UUVJLJ2P","stars":2,"destructionPercentage":76,"order":8}],"opponentAttacks":1,"bestOpponentAttack":{"attackerTag":"#82P89CU2","defenderTag":"#Y8G828QVL","stars":2,"destructionPercentage":93,"order":16}},{"tag":"#9LJJUYUJQ","name":"BLACK PANTHER","townhallLevel":13,"mapPosition":24,"attacks":[{"attackerTag":"#9LJJUYUJQ","defenderTag":"#8GPCP09P","stars":2,"destructionPercentage":52,"order":40}],"opponentAttacks":1,"bestOpponentAttack":{"attackerTag":"#8JY9RL2CU","defenderTag":"#9LJJUYUJQ","stars":3,"destructionPercentage":100,"order":27}}]},"warStartTime":"20200802T144423.000Z"}